plotcp/__init__.py
plotcp/enums.py
plotcp/plot_complex_points.py
plotcp/plotcp.py
plotcp-0.3.1.dist-info/LICENSE
plotcp-0.3.1.dist-info/WHEEL
plotcp-0.3.1.dist-info/METADATA
plotcp-0.3.1.dist-info/RECORD
