Metadata-Version: 2.1
Name: plotcp
Version: 0.3.1
Summary: Python package for drawing transformations of functions of a complex variable of the whole grid or a given area
Home-page: https://github.com/ZettZet/plotcp
License: AGPL-3.0
Author: ZetZet
Author-email: dmesser@yandex.ru
Requires-Python: >=3.8,<4.0
Classifier: License :: OSI Approved :: GNU Affero General Public License v3
Classifier: Programming Language :: Python :: 3
Classifier: Programming Language :: Python :: 3.8
Classifier: Topic :: Scientific/Engineering :: Visualization
Requires-Dist: matplotlib (>=3.2.1,<4.0.0)
Requires-Dist: numpy (>=1.18.4,<2.0.0)
Project-URL: Repository, https://github.com/ZettZet/plotcp
